Workbook

Sheet WBS Project
B1: WORK BREAKDOWN STRUCTURE
B3: PROJECT TITLE | E3: START DATE
B4: Pet Adoption Website
B5: PROJECT MANAGER | E5: END DATE | G5: PROJECT DURATION
B8: ID | C8: TASK | D8: DESCRIPTION | E8: START DATE | F8: END DATE | G8: DURATION | H8: COMMENTS
B10: 1 | C10: Phase 1 - Planning
B11: 1.1 | C11: Define Project Scope & Requirements | D11: Document project goals, features, and requirements for the pet adoption platform.
B12: 1.2 | C12: Create Project Timeline | D12: Develop schedule with milestones and deadlines for project completion.
B13: 1.3 | C13: Allocate Resources & Team Roles | D13: Assign team members to roles and distribute project resources.
B15: 2 | C15: Phase 2 - Design
B16: 2.1 | C16: Research & Analysis | D16: Study existing pet adoption platforms and identify user needs.
B17: 2.2 | C17: Develop Wireframes & Prototypes | D17: Create basic layout designs and clickable prototypes.
B18: 2.3 | C18: Design Website Layout & UI | D18: Design user interface elements and page layouts.
B19: 2.4 | C19: Create Branding Elements | D19: Design logo, select colors, and establish visual identity.
B21: 3 | C21: Phase 3 - Development
B22: 3.1 | C22: Set Up Development Environment | D22: Configure development tools, servers, and databases.
B23: 3.2 | C23: Backend Development | D23: Build server-side functionality and database structure
B24: 3.3 | C24: Frontend Development | D24: Create user interface and implement responsive design.
B26: 4 | C26: Phase 4 - Testing and Demo
B27: 4.1 | C27: Functional Testing | D27: Test all platform features and functionality.
B28: 4.2 | C28: User Acceptance Test UAT | D28: Conduct testing with sample users to validate platform.
B29: 4.3 | C29: Bug Fixing & Re-testing | D29: Fix identified issues and perform regression testing
B30: 4.4 | C30: Demonstration | D30: Present completed platform to stakeholders.

Sheet WBS Phase 3
B1: WORK BREAKDOWN STRUCTURE
B3: PHASE 3 | E3: START DATE
B4: Development
B5: LEAD | E5: END DATE | G5: PHASE DURATION
B8: ID | C8: TASK | D8: DESCRIPTION | E8: START DATE | F8: END DATE | G8: DURATION | H8: COMMENTS
B10: 3.1 | C10: Account Management
B11: 3.1.1 | C11: Edit Profile Name | D11: Allow users to update their display name on their account.
B12: 3.1.2 | C12: Edit Picture | D12: Enable users to upload and change their profile picture.
B13: 3.1.3 | C13: Change Password | D13: Provide functionality for users to update their account password securely.
B15: 3.2 | C15: Pet Browsing
B16: 3.2.1 | C16: Browsing | D16: Display a grid/list view of available pets for adoption.
B17: 3.2.2 | C17: Filtering and Searching | D17: Enable users to search pets by criteria like breed, location.
B18: 3.2.3 | C18: Accessing Pet Details | D18: View information about individual pets including photos and descriptions.
B20: 3.3 | C20: Pet Management
B21: 3.3.1 | C21: Uploading Pet | D21: Allow staff to add new pets to the adoption platform
B22: 3.3.2 | C22: Deleting Pet | D22: Enable removal of pet listings once they're adopted or no longer available.
B23: 3.3.3 | C23: Editing Pet Information | D23: Update pet details, photos, and adoption status
B25: 3.4 | C25: Authentication
B26: 3.4.1 | C26: Login | D26: Securely access user accounts with email/username and password.
B27: 3.4.2 | C27: Registration | D27: Create new user accounts with basic profile information.

Sheet WBS Phase 3v2
B1: WORK BREAKDOWN STRUCTURE
B3: PHASE 3 | E3: START DATE
B4: Development
B5: LEAD | E5: END DATE | G5: PHASE DURATION
B8: ID | C8: TASK | D8: DESCRIPTION | E8: START DATE | F8: END DATE | G8: DURATION | H8: COMMENTS
B10: 3.1 | C10: Account Management
B11: 3.1.1 | C11: Edit Profile Name | D11: Allow users to update their display name on their account.
B12: 3.1.2 | C12: Edit Picture | D12: Enable users to upload and change their profile picture.
B13: 3.1.3 | C13: Change Password | D13: Provide functionality for users to update their account password securely.
B15: 3.2 | C15: Pet Browsing
B16: 3.2.1 | C16: Browsing | D16: Display a grid/list view of available pets for adoption.
B17: 3.2.2 | C17: Filtering and Searching | D17: Enable users to search pets by criteria like breed, location.
B18: 3.2.3 | C18: Accessing Pet Details | D18: View information about individual pets including photos and descriptions.
B20: 3.3 | C20: Pet Management
B21: 3.3.1 | C21: Uploading Pet | D21: Allow staff to add new pets to the adoption platform
B22: 3.3.2 | C22: Deleting Pet | D22: Enable removal of pet listings once they're adopted or no longer available.
B23: 3.3.3 | C23: Editing Pet Information | D23: Update pet details, photos, and adoption status
B25: 3.4 | C25: Authentication
B26: 3.4.1 | C26: Login | D26: Securely access user accounts with email/username and password.
B27: 3.4.2 | C27: Registration | D27: Create new user accounts with basic profile information.

Sheet Gantt Chart
B1: GANTT CHART
B3: PROJECT TITLE | D3: START DATE | F3: DISPLAY WEEK
B4: SafeSight | D4: 46042 | F4: 1
B5: PROJECT MANAGER | D5: END DATE | F5: PROJECT DURATION
B6: Sandali Silva | D6: 45757 | F6: 3 Months
I8: =I9 -> 46041 | P8: =P9 -> 46048 | W8: =W9 -> 46055 | AD8: =AD9 -> 46062 | AK8: =AK9 -> 46069 | AR8: =AR9 -> 46076 | AY8: =AY9 -> 46083 | BF8: =BF9 -> 46090 | BM8: =BM9 -> 46097 | BT8: =BT9 -> 46104 | CA8: =CA9 -> 46111
I9: =$D$4-WEEKDAY(D4,3) + (F4-1)*7 -> 46041 | J9: =I9+1 -> 46042 | K9: =J9+1 -> 46043 | L9: =K9+1 -> 46044 | M9: =L9+1 -> 46045 | N9: =M9+1 -> 46046 | O9: =N9+1 -> 46047 | P9: =O9+1 -> 46048 | Q9: =P9+1 -> 46049 | ... CG9: =CF9+1 -> 46117
C10: TASK | E10: START DATE | F10: DAYS | G10: END DATE | I10: =LEFT(TEXT(I9,"ddd")) -> M | J10: =LEFT(TEXT(J9,"ddd")) -> T | K10: =LEFT(TEXT(K9,"ddd")) -> W | L10: =LEFT(TEXT(L9,"ddd")) -> T | M10: =LEFT(TEXT(M9,"ddd")) -> F | N10: =LEFT(TEXT(N9,"ddd")) -> S | O10: =LEFT(TEXT(O9,"ddd")) -> S | P10: =LEFT(TEXT(P9,"ddd")) -> M | ... CG10: =LEFT(TEXT(CG9,"ddd")) -> S
B12: 1 | C12: Domain Analysis & Requirements | E12: =MIN(E13:E15) -> 46042 | G12: =MAX(G13:G15) -> 46049
B13: 1.1 | C13: Define Project Scope & Requirements | D13: =IFERROR(__xludf.DUMMYFUNCTION("IFERROR(SPARKLINE(D10,{""charttype"",""bar""; ""color1"", ""green"";""max"", 1}))"),"") | E13: 46042 | F13: 5 | G13: =(E13+F13) - 1 -> 46046
B14: 1.2 | C14: Create Project Timeline | D14: =IFERROR(__xludf.DUMMYFUNCTION("IFERROR(SPARKLINE(D11,{""charttype"",""bar""; ""color1"", ""green"";""max"", 1}))"),"") | E14: 46047 | F14: 1 | G14: =(E14+F14) - 1 -> 46047
B15: 1.3 | C15: Allocate Resources | E15: 46047 | F15: 1 | G15: =(E15+F15) + 1 -> 46049
B17: 2 | C17: System Design & Development | E17: =MIN(E18:E21) -> 46049 | G17: =MAX(G18:G21) -> 46082
B18: 2.1 | C18: Research & Analysis | E18: 46049 | F18: 7 | G18: =(E18+F18) - 1 -> 46055
B19: 2.2 | C19: Develop Wireframes & Prototypes | D19: =IFERROR(__xludf.DUMMYFUNCTION("IFERROR(SPARKLINE(D21,{""charttype"",""bar""; ""color1"", ""green"";""max"", 1}))"),"") | E19: 46056 | F19: 14 | G19: =(E19+F19) - 1 -> 46069
B20: 2.3 | C20: Design Website Layout & UI | E20: 46069 | F20: 10 | G20: =(E20+F20) + 1 -> 46080
B21: 2.4 | C21: Create Branding Elements | E21: 46081 | F21: 2 | G21: =(E21+F21) - 1 -> 46082
B23: 3 | C23: Development | E23: =MIN(E25:E39) -> 46088 | G23: =MAX(G25:G39) -> 46115
B24: 3.1 | C24: Frontend Development | E24: 46082 | F24: 7 | G24: 46088
B25: 3.2 | C25: Backend API Development | E25: 46088 | F25: 4 | G25: =(E25+F25) - 1 -> 46091
B26: 3.3 | C26: Registration | E26: 46091 | F26: 5 | G26: =(E26+F26) - 1 -> 46095
B27: 3.4 | C27: Authentication & Role Management | E27: 46095 | F27: 2 | G27: 46097
B28: 3.5 | C28: WorkSafeBC Report Automation | E28: 46093 | F28: 2 | G28: =(E28+F28) - 1 -> 46094
B29: 3.6 | C29: Data Collection & Cleaning | E29: 46094 | F29: 3 | G29: =(E29+F29) - 1 -> 46096
B30: 3.7 | C30: Feature Engineering & Data Prep | E30: 46097 | F30: 4 | G30: =(E30+F30) - 1 -> 46100
B31: 3.8 | C31: Predictive Model Development | E31: 46100 | F31: 4 | G31: =(E31+F31) - 1 -> 46103
B32: 3.9 | C32: Model Training & Validation | E32: 46101 | F32: 5 | G32: =(E32+F32) - 1 -> 46105
B33: 3.1 | C33: Prediction API Integration | E33: 46105 | F33: 7 | G33: =(E33+F33) - 1 -> 46111
B34: 3.11 | C34: Dashboard | E34: 46106 | F34: 7 | G34: =(E34+F34) - 1 -> 46112
B35: 3.12 | C35: Visualizations | E35: 46107 | F35: 3 | G35: =(E35+F35) - 1 -> 46109
B36: 3.13 | C36: Account Management | E36: 46107 | F36: 2 | G36: =(E36+F36) - 1 -> 46108
B37: 3.14 | C37: Edit Profile | E37: 46108 | F37: 7 | G37: =(E37+F37) - 1 -> 46114
B38: 3.15 | C38: HR departmental view | E38: 46109 | F38: 7 | G38: =(E38+F38) - 1 -> 46115
B39: 3.16 | C39: Report Generation | E39: 46110 | F39: 2 | G39: =(E39+F39) - 1 -> 46111
B41: 4 | C41: Testing and Demo | E41: =MIN(E42:E45) -> 46111 | G41: =MAX(G42:G45) -> 46120
B42: 4.1 | C42: Functional Testing | E42: 46111 | F42: 2 | G42: =(E42+F42) - 1 -> 46112
B43: 4.2 | C43: User Acceptance Test UAT | E43: 46112 | F43: 1 | G43: =(E43+F43) - 1 -> 46112
B44: 4.3 | C44: Bug Fixing & Re-testing | E44: 46113 | F44: 3 | G44: =(E44+F44) - 1 -> 46115
B45: 4.4 | C45: Demonstration & Submission | E45: 46120 | F45: 1 | G45: =(E45+F45) - 1 -> 46120

Sheet Scheduling Critical Path
B1: SCHEDULING TASK
B3: TASK | C3: 3.2 | E3: START DATE
B4: Pet Management
B5: LEAD | E5: END DATE | G5: TASK DURATION
G6: 15
B8: ID | C8: ACTIVITY | D8: PREDECESSOR | E8: DURATION | F8: RESPON | G8: ES | H8: EF | I8: LS | J8: LF | K8: SLACK | L8: CRITICAL | N8: ES | P8: EF
N9: Activity Description
B10: 1 | C10: Develop Pet model in back-end | E10: 1 | F10: Ian | G10: 0 | H10: =G10+E10 -> 1 | I10: =J10-E10 -> 0 | J10: =MIN(I11:I14) -> 1 | K10: =I10-G10 -> 0 | L10: =IF(K10<=0,"Yes","No") -> Yes
B11: 2 | C11: Develop POST endpoint for pet | D11: 1 | E11: 2 | F11: Ian | G11: =H10 -> 1 | H11: =G11+E11 -> 3 | I11: =J11-E11 -> 2 | J11: =I15 -> 4 | K11: =I11-G11 -> 1 | L11: =IF(K11<=0,"Yes","No") -> No | N11: ID | O11: R | P11: D
B12: 3 | C12: Develop DELETE endpoint for pet | D12: 1 | E12: 2 | F12: Ian | G12: =H10 -> 1 | H12: =G12+E12 -> 3 | I12: =J12-E12 -> 2 | J12: =I15 -> 4 | K12: =I12-G12 -> 1 | L12: =IF(K12<=0,"Yes","No") -> No | N12: LS | P12: LF
B13: 4 | C13: Develop PUT endpoint for pet | D13: 1 | E13: 2 | F13: Ian | G13: =H10 -> 1 | H13: =G13+E13 -> 3 | I13: =J13-E13 -> 2 | J13: =I15 -> 4 | K13: =I13-G13 -> 1 | L13: =IF(K13<=0,"Yes","No") -> No
B14: 5 | C14: Develop GET endpoint for pet | D14: 1 | E14: 3 | F14: Ian | G14: =H10 -> 1 | H14: =G14+E14 -> 4 | I14: =J14-E14 -> 1 | J14: =I15 -> 4 | K14: =I14-G14 -> 0 | L14: =IF(K14<=0,"Yes","No") -> Yes | N14: ES | O14: Earliest Start
B15: 6 | C15: Handle image saving and deleting | D15: 2, 3, 4, 5 | E15: 1 | F15: Ian | G15: =MAX(H11:H14) -> 4 | H15: =G15+E15 -> 5 | I15: =J15-E15 -> 4 | J15: =MIN(I16:I17) -> 5 | K15: =I15-G15 -> 0 | L15: =IF(K15<=0,"Yes","No") -> Yes | N15: EF | O15: Earliest Finish
B16: 7 | C16: Testing backend | D16: 6 | E16: 2 | F16: Tommy | G16: =H15 -> 5 | H16: =G16+E16 -> 7 | I16: =J16-E16 -> 5 | J16: =I18 -> 7 | K16: =I16-G16 -> 0 | L16: =IF(K16<=0,"Yes","No") -> Yes | N16: LS | O16: Latest Start
B17: 8 | C17: Wireframe for pet management layout | D17: 6 | E17: 1 | F17: Upul | G17: =H15 -> 5 | H17: =G17+E17 -> 6 | I17: =J17-E17 -> 6 | J17: =I18 -> 7 | K17: =I17-G17 -> 1 | L17: =IF(K17<=0,"Yes","No") -> No | N17: LF | O17: Latest Finish
B18: 9 | C18: Develop front-end interfaces and forms | D18: 7, 8 | E18: 4 | F18: Ian | G18: =MAX(H16:H17) -> 7 | H18: =G18+E18 -> 11 | I18: =J18-E18 -> 7 | J18: =I19 -> 11 | K18: =I18-G18 -> 0 | L18: =IF(K18<=0,"Yes","No") -> Yes | N18: ID | O18: Activity Number
B19: 10 | C19: Integrating front-end with back-end | D19: 9 | E19: 2 | F19: Ian | G19: =H18 -> 11 | H19: =G19+E19 -> 13 | I19: =J19-E19 -> 11 | J19: =I20 -> 13 | K19: =I19-G19 -> 0 | L19: =IF(K19<=0,"Yes","No") -> Yes | N19: D | O19: Estimated Duration
B20: 11 | C20: Testing integration | D20: 10 | E20: 2 | F20: Tommy | G20: =H19 -> 13 | H20: =G20+E20 -> 15 | I20: =J20-E20 -> 13 | J20: =G6 -> 15 | K20: =I20-G20 -> 0 | L20: =IF(K20<=0,"Yes","No") -> Yes | N20: R | O20: Responsible Person

Sheet Sheet1
A1: SCHEDULING TASK
A3: TASK | B3: 3.2 | D3: START DATE
A4: Pet Management
A5: LEAD | D5: END DATE | F5: TASK DURATION
F6: 15
A8: ID | B8: ACTIVITY | C8: PREDECESSOR | D8: DURATION | E8: RESPON | F8: ES | G8: EF | H8: LS | I8: LF | J8: SLACK | K8: CRITICAL
A10: 1 | B10: Develop Pet model in back-end | D10: 1 | E10: Ian | F10: 0 | G10: =F10+D10 -> 1 | H10: =I10-D10 -> 0 | I10: =MIN(H11:H14) -> 1 | J10: =H10-F10 -> 0 | K10: =IF(J10<=0,"Yes","No") -> Yes
A11: 2 | B11: Develop POST endpoint for pet | C11: 1 | D11: 2 | E11: Ian | F11: =G10 -> 1 | G11: =F11+D11 -> 3 | H11: =I11-D11 -> 2 | I11: =H15 -> 4 | J11: =H11-F11 -> 1 | K11: =IF(J11<=0,"Yes","No") -> No
A12: 3 | B12: Develop DELETE endpoint for pet | C12: 1 | D12: 2 | E12: Ian | F12: =G10 -> 1 | G12: =F12+D12 -> 3 | H12: =I12-D12 -> 2 | I12: =H15 -> 4 | J12: =H12-F12 -> 1 | K12: =IF(J12<=0,"Yes","No") -> No
A13: 4 | B13: Develop PUT endpoint for pet | C13: 1 | D13: 2 | E13: Ian | F13: =G10 -> 1 | G13: =F13+D13 -> 3 | H13: =I13-D13 -> 2 | I13: =H15 -> 4 | J13: =H13-F13 -> 1 | K13: =IF(J13<=0,"Yes","No") -> No
A14: 5 | B14: Develop GET endpoint for pet | C14: 1 | D14: 3 | E14: Ian | F14: =G10 -> 1 | G14: =F14+D14 -> 4 | H14: =I14-D14 -> 1 | I14: =H15 -> 4 | J14: =H14-F14 -> 0 | K14: =IF(J14<=0,"Yes","No") -> Yes
A15: 6 | B15: Handle image saving and deleting | C15: 2, 3, 4, 5 | D15: 1 | E15: Ian | F15: =MAX(G11:G14) -> 4 | G15: =F15+D15 -> 5 | H15: =I15-D15 -> 4 | I15: =MIN(H16:H17) -> 5 | J15: =H15-F15 -> 0 | K15: =IF(J15<=0,"Yes","No") -> Yes
A16: 7 | B16: Testing backend | C16: 6 | D16: 2 | E16: Tommy | F16: =G15 -> 5 | G16: =F16+D16 -> 7 | H16: =I16-D16 -> 5 | I16: =H18 -> 7 | J16: =H16-F16 -> 0 | K16: =IF(J16<=0,"Yes","No") -> Yes
A17: 8 | B17: Wireframe for pet management layout | C17: 6 | D17: 1 | E17: Upul | F17: =G15 -> 5 | G17: =F17+D17 -> 6 | H17: =I17-D17 -> 6 | I17: =H18 -> 7 | J17: =H17-F17 -> 1 | K17: =IF(J17<=0,"Yes","No") -> No
A18: 9 | B18: Develop front-end interfaces and forms | C18: 7, 8 | D18: 4 | E18: Ian | F18: =MAX(G16:G17) -> 7 | G18: =F18+D18 -> 11 | H18: =I18-D18 -> 7 | I18: =H19 -> 11 | J18: =H18-F18 -> 0 | K18: =IF(J18<=0,"Yes","No") -> Yes
A19: 10 | B19: Integrating front-end with back-end | C19: 9 | D19: 2 | E19: Ian | F19: =G18 -> 11 | G19: =F19+D19 -> 13 | H19: =I19-D19 -> 11 | I19: =H20 -> 13 | J19: =H19-F19 -> 0 | K19: =IF(J19<=0,"Yes","No") -> Yes
A20: 11 | B20: Testing integration | C20: 10 | D20: 2 | E20: Tommy | F20: =G19 -> 13 | G20: =F20+D20 -> 15 | H20: =I20-D20 -> 13 | I20: =F6 -> 15 | J20: =H20-F20 -> 0 | K20: =IF(J20<=0,"Yes","No") -> Yes

Sheet Network Diagram
B1: SCHEDULE NETWORK DIAGRAM
B4: ='Scheduling Critical Path'!$G10 -> 0 | D4: =B4+D6 -> 1 | F4: ='Scheduling Critical Path'!G11 -> 1 | H4: =F4+H6 -> 3
B5: ='Scheduling Critical Path'!$C10 -> Develop Pet model in back-end | F5: ='Scheduling Critical Path'!$C11 -> Develop POST endpoint for pet
B6: ='Scheduling Critical Path'!$B10 -> 1 | C6: ='Scheduling Critical Path'!$F10 -> Ian | D6: ='Scheduling Critical Path'!$E10 -> 1 | F6: ='Scheduling Critical Path'!$B11 -> 2 | G6: ='Scheduling Critical Path'!$F11 -> Ian | H6: ='Scheduling Critical Path'!$E11 -> 2
B7: =D7-D6 -> 0 | D7: ='Scheduling Critical Path'!$J10 -> 1 | F7: =H7-H6 -> 2 | H7: ='Scheduling Critical Path'!J11 -> 4
B9: ='Scheduling Critical Path'!G12 -> 1 | D9: =B9+D11 -> 3 | F9: ='Scheduling Critical Path'!G13 -> 1 | H9: =F9+H11 -> 3
B10: ='Scheduling Critical Path'!$C12 -> Develop DELETE endpoint for pet | F10: ='Scheduling Critical Path'!$C13 -> Develop PUT endpoint for pet
B11: ='Scheduling Critical Path'!$B12 -> 3 | C11: ='Scheduling Critical Path'!$F12 -> Ian | D11: ='Scheduling Critical Path'!$E12 -> 2 | F11: ='Scheduling Critical Path'!$B13 -> 4 | G11: ='Scheduling Critical Path'!$F13 -> Ian | H11: ='Scheduling Critical Path'!$E13 -> 2
B12: =D12-D11 -> 2 | D12: ='Scheduling Critical Path'!J12 -> 4 | F12: =H12-H11 -> 2 | H12: ='Scheduling Critical Path'!J13 -> 4
B14: ='Scheduling Critical Path'!G14 -> 1 | D14: =B14+D16 -> 4 | F14: ='Scheduling Critical Path'!G15 -> 4 | H14: =F14+H16 -> 5
B15: ='Scheduling Critical Path'!$C14 -> Develop GET endpoint for pet | F15: ='Scheduling Critical Path'!$C15 -> Handle image saving and deleting
B16: ='Scheduling Critical Path'!$B14 -> 5 | C16: ='Scheduling Critical Path'!$F14 -> Ian | D16: ='Scheduling Critical Path'!$E14 -> 3 | F16: ='Scheduling Critical Path'!$B15 -> 6 | G16: ='Scheduling Critical Path'!$F15 -> Ian | H16: ='Scheduling Critical Path'!$E15 -> 1
B17: =D17-D16 -> 1 | D17: ='Scheduling Critical Path'!J14 -> 4 | F17: =H17-H16 -> 4 | H17: ='Scheduling Critical Path'!J15 -> 5
B19: ='Scheduling Critical Path'!G16 -> 5 | D19: =B19+D21 -> 7 | F19: ='Scheduling Critical Path'!G17 -> 5 | H19: =F19+H21 -> 6
B20: ='Scheduling Critical Path'!$C16 -> Testing backend | F20: ='Scheduling Critical Path'!$C17 -> Wireframe for pet management layout
B21: ='Scheduling Critical Path'!$B16 -> 7 | C21: ='Scheduling Critical Path'!$F16 -> Tommy | D21: ='Scheduling Critical Path'!$E16 -> 2 | F21: ='Scheduling Critical Path'!$B17 -> 8 | G21: ='Scheduling Critical Path'!$F17 -> Upul | H21: ='Scheduling Critical Path'!$E17 -> 1
B22: =D22-D21 -> 5 | D22: ='Scheduling Critical Path'!J16 -> 7 | F22: =H22-H21 -> 6 | H22: ='Scheduling Critical Path'!J17 -> 7
B24: ='Scheduling Critical Path'!G18 -> 7 | D24: =B24+D26 -> 11 | F24: ='Scheduling Critical Path'!G19 -> 11 | H24: =F24+H26 -> 13
B25: ='Scheduling Critical Path'!$C18 -> Develop front-end interfaces and forms | F25: ='Scheduling Critical Path'!$C19 -> Integrating front-end with back-end
B26: ='Scheduling Critical Path'!$B18 -> 9 | C26: ='Scheduling Critical Path'!$F18 -> Ian | D26: ='Scheduling Critical Path'!$E18 -> 4 | F26: ='Scheduling Critical Path'!$B19 -> 10 | G26: ='Scheduling Critical Path'!$F19 -> Ian | H26: ='Scheduling Critical Path'!$E19 -> 2
B27: =D27-D26 -> 7 | D27: ='Scheduling Critical Path'!J18 -> 11 | F27: =H27-H26 -> 11 | H27: ='Scheduling Critical Path'!J19 -> 13
B29: ='Scheduling Critical Path'!G20 -> 13 | D29: =B29+D31 -> 15
B30: ='Scheduling Critical Path'!$C20 -> Testing integration
B31: ='Scheduling Critical Path'!$B20 -> 11 | C31: ='Scheduling Critical Path'!$F20 -> Tommy | D31: ='Scheduling Critical Path'!$E20 -> 2
B32: =D32-D31 -> 13 | D32: ='Scheduling Critical Path'!J20 -> 15

Sheet Backlog and Sprints
B2: Sprint Breakdown (Focused Themes)
B3: Sprint | C3: Theme | D3: User Story | E3: Priority | F3: Status | G3: Components
A4: =ROW()-3 -> 1 | B4: Sprint 1 | C4: Pet Management | D4: As a pet owner, I want to add new pets to the system | E4: High | F4: Done | G4: PetController, ManagementDashboard
A5: =ROW()-3 -> 2 | B5: Sprint 1 | C5: Pet Management | D5: As a pet owner, I want to edit my pet listings | E5: High | F5: Done | G5: PetController, ManagementDashboard
A6: =ROW()-3 -> 3 | B6: Sprint 1 | C6: Pet Management | D6: As a pet owner, I want to delete my pet listings | E6: High | F6: Done | G6: PetController, ManagementDashboard
A7: =ROW()-3 -> 4 | B7: Sprint 1 | E7: High | F7: Done | G7: PetController, ManagementDashboard
A8: =ROW()-3 -> 5 | B8: Sprint 1 | C8: Pet Management | D8: As a user, I want to view all pets up for adoption in a single web page. | E8: Medium | F8: Done | G8: PetController, SimplePetDTO
A9: =ROW()-3 -> 6 | B9: Sprint 2 | C9: Authentication | D9: As a user, I want to create an account | E9: High | F9: Done | G9: UserController, UserRepository
A10: =ROW()-3 -> 7 | B10: Sprint 2 | C10: Authentication | D10: As a user, I want to login to my account | E10: High | F10: Done | G10: LoginController, AuthenticationService
A11: =ROW()-3 -> 8 | B11: Sprint 2 | C11: Authentication | D11: As a system, I want to encrypt passwords | E11: High | F11: Done | G11: PasswordEncrypter
A12: =ROW()-3 -> 9 | B12: Sprint 3 | C12: Enhancements | D12: As a user, I want to filter pets by type/size/location | E12: Medium | F12: To Do | G12: PetRepository
A13: =ROW()-3 -> 10 | B13: Sprint 3 | C13: Enhancements | D13: As a user, I want to view detailed pet profiles to learn more about potential adoptees. Acceptance Criteria: | E13: Medium | F13: To Do | G13: DetailedPetDTO
A14: =ROW()-3 -> 11 | B14: Sprint 3 | D14: As a user, I want to view and give ratings for the shelters based on the experience of adopting. | E14: Medium | F14: To Do | G14: Frontend components
D15: As a user, I want to inquire about pets I'm interested in adopting.
C23: Theme | D23: User Story | E23: Sprint | F23: Priority | G23: Status
C24: Authentication | D24: US1 - Registration | E24: 1 | F24: High | G24: Done
C25: Authentication | D25: US2 - Login | E25: 1 | F25: High | G25: Done
C26: Pet Management | D26: US3 - Uploading Pet | E26: 1 | F26: High | G26: Done
C27: Pet Management | D27: US4 - Deleting Pet | E27: 2 | F27: High | G27: Done
C28: Pet Management | D28: US5 - Editing Pet | E28: 2 | F28: High | G28: Done
C29: Pet Browsing | D29: US6 - Guest Browsing | E29: 2 | F29: High | G29: Done
C30: Pet Browsing | D30: US7 - Filtering and Searching | E30: 3 | F30: Medium | G30: To Do
C31: Pet Browsing | D31: US8 - Pet Inquiries | E31: 3 | F31: Medium | G31: To Do
C32: Account Management | D32: US10 - Edit Profile Name and Details | E32: 4 | F32: Medium | G32: To Do
C33: Account Management | D33: US11 - Change Password | E33: 4 | F33: Low | G33: To Do
C34: Account Management | D34: US12 - Edit Profile Picture | E34: 4 | F34: Low | G34: To Do
C35: Pet Browsing | D35: US9 - Shelter Rating System | E35: 4 | F35: Low | G35: To Do

Sheet Business Case Financials
B2: Year 2
A3: Month Number | B3: 1 | C3: 2 | D3: 3 | E3: 4 | F3: 5 | G3: 6 | H3: 7 | I3: 8 | J3: 9 | K3: 10 | L3: 11 | M3: 12 | N3: Year 2
A5: Active Registrations - Opening | B5: 0 | C5: =B7 -> 13.333333 | D5: =C7 -> 26.666667 | E5: =D7 -> 40 | F5: =E7 -> 45 | G5: =F7 -> 50 | H5: =G7 -> 55 | I5: =H7 -> 60 | J5: =I7 -> 65 | ... M5: =L7 -> 80
A6: Net Addition | B6: =200*20%/3 -> 13.333333 | C6: =200*20%/3 -> 13.333333 | D6: =200*20%/3 -> 13.333333 | E6: =B21 -> 5 | F6: 5 | G6: 5 | H6: 5 | I6: 5 | J6: 5 | K6: 5 | L6: 5 | M6: 5
A7: Active Registrations - Closing | B7: =SUM(B5:B6) -> 13.333333 | C7: =SUM(C5:C6) -> 26.666667 | D7: =SUM(D5:D6) -> 40 | E7: =SUM(E5:E6) -> 45 | F7: =SUM(F5:F6) -> 50 | G7: =SUM(G5:G6) -> 55 | H7: =SUM(H5:H6) -> 60 | I7: =SUM(I5:I6) -> 65 | ... M7: =SUM(M5:M6) -> 85 | N7: =M7 -> 85
A9: Subscription Rate | B9: 39 | C9: =B9 -> 39 | D9: =C9 -> 39 | E9: =D9 -> 39 | F9: =E9 -> 39 | G9: =F9 -> 39 | H9: =G9 -> 39 | I9: =H9 -> 39 | J9: =I9 -> 39 | ... M9: =L9 -> 39
A11: Revenue | B11: =AVERAGE(B5,B7)*B9 -> 260 | C11: =AVERAGE(C5,C7)*C9 -> 780 | D11: =AVERAGE(D5,D7)*D9 -> 1300 | E11: =AVERAGE(E5,E7)*E9 -> 1657.5 | F11: =AVERAGE(F5,F7)*F9 -> 1852.5 | G11: =AVERAGE(G5,G7)*G9 -> 2047.5 | H11: =AVERAGE(H5,H7)*H9 -> 2242.5 | I11: =AVERAGE(I5,I7)*I9 -> 2437.5 | ... M11: =AVERAGE(M5,M7)*M9 -> 3217.5 | N11: =SUM(B11:M11) -> 24277.5
A12: Website Hosting and Maintenance Cost | B12: =-B19 -> -300 | C12: =B12*1.03 -> -309 | D12: =C12*1.03 -> -318.27 | E12: =D12*1.03 -> -327.8181 | F12: =E12*1.03 -> -337.65264 | G12: =F12*1.03 -> -347.78222 | H12: =G12*1.03 -> -358.21569 | I12: =H12*1.03 -> -368.96216 | J12: =I12*1.03 -> -380.03102 | ... M12: =L12*1.03 -> -415.27016 | N12: =SUM(B12:M12) -> -4257.6089
A13: Sales and Marketing Cost | B13: =B22*-1*0.5 -> -1000 | C13: =B22*-1*0.25 -> -500 | D13: -500 | N13: =SUM(B13:M13) -> -2000
A14: Profit | B14: =SUM(B11:B13) -> -1040 | C14: =SUM(C11:C13) -> -29 | D14: =SUM(D11:D13) -> 481.73 | E14: =SUM(E11:E13) -> 1329.6819 | F14: =SUM(F11:F13) -> 1514.8474 | G14: =SUM(G11:G13) -> 1699.7178 | H14: =SUM(H11:H13) -> 1884.2843 | I14: =SUM(I11:I13) -> 2068.5378 | ... N14: =SUM(N11:N13) -> 18019.891
A17: Assumptions
A19: Running cost of the Website per month | B19: 300
A20: Average net addition for 1-3 months | B20: 13
A21: Average net addition for 4 month onwards | B21: 5
A22: Sales and Marketing Investment | B22: 2000
